PyGT/GT.py
PyGT/__init__.py
PyGT/io.py
PyGT/mfpt.py
PyGT/spectral.py
PyGT/stats.py
PyGT/tools.py
PyGT-0.3.0.dist-info/LICENSE
PyGT-0.3.0.dist-info/METADATA
PyGT-0.3.0.dist-info/WHEEL
PyGT-0.3.0.dist-info/top_level.txt
PyGT-0.3.0.dist-info/RECORD
