Metadata-Version: 2.1
Name: PyGT
Version: 0.3.0
Summary: Graph transformation and reduction in Python
Home-page: https://github.com/tomswinburne/PyGT
Author: TD Swinburne
Author-email: swinburne@cinam.univ-mrs.fr
License: UNKNOWN
Platform: UNKNOWN
Classifier: Programming Language :: Python :: 3
Classifier: License :: OSI Approved :: MIT License
Classifier: Operating System :: OS Independent
Requires-Python: >=3.6
Requires-Dist: scipy (>=1.5)
Requires-Dist: numpy (>=1.17)
Requires-Dist: matplotlib (>=3)
Requires-Dist: tqdm (>=4.47)
Requires-Dist: pathos (>=0.2)
